[
 {
  "input": "Experiments with toy SIR models",
  "translatedText": "Experimentos con modelos SIR de juguete.",
  "n_reviews": 0
 },
 {
  "input": "Help fund future projects: https://www.patreon.com/3blue1brown",
  "translatedText": "Ayude a financiar proyectos futuros: https://www.patreon.com/3blue1brown",
  "n_reviews": 0
 },
 {
  "input": "An equally valuable form of support is to simply share some of the videos.",
  "translatedText": "Una forma de apoyo igualmente valiosa es simplemente compartir algunos de los vídeos.",
  "n_reviews": 0
 },
 {
  "input": "Special thanks to these supporters: http://3b1b.co/sir-thanks",
  "translatedText": "Un agradecimiento especial a estos seguidores: http://3b1b.co/sir-thanks",
  "n_reviews": 0
 },
 {
  "input": "Home page: https://www.3blue1brown.com\r",
  "translatedText": "Página de inicio: https://www.3blue1brown.com\r",
  "n_reviews": 0
 },
 {
  "input": "\r",
  "translatedText": "\r",
  "n_reviews": 0
 },
 {
  "input": "Awesome fan-made interactives:",
  "translatedText": "Impresionantes interactivos hechos por fans:",
  "n_reviews": 0
 },
 {
  "input": "https://prajwalsouza.github.io/Experiments/Epidemic-Simulation.html",
  "translatedText": "https://prajwalsouza.github.io/Experiments/Epidemic-Simulation.html",
  "n_reviews": 0
 },
 {
  "input": "https://learningsim.itch.io/pandemic-spread-simulation",
  "translatedText": "https://learningsim.itch.io/pandemic-spread-simulation",
  "n_reviews": 0
 },
 {
  "input": "",
  "translatedText": "",
  "n_reviews": 0
 },
 {
  "input": "Simulations by Harry Stevens at the Washington Post:",
  "translatedText": "Simulaciones de Harry Stevens en el Washington Post:",
  "n_reviews": 0
 },
 {
  "input": "https://www.washingtonpost.com/graphics/2020/world/corona-simulator/",
  "translatedText": "https://www.washingtonpost.com/graphics/2020/world/corona-simulator/",
  "n_reviews": 0
 },
 {
  "input": "",
  "translatedText": "",
  "n_reviews": 0
 },
 {
  "input": "Simulations by Kevin Simler at Melting Asphalt:",
  "translatedText": "Simulaciones de Kevin Simler en Melting Asphalt:",
  "n_reviews": 0
 },
 {
  "input": "https://meltingasphalt.com/interactive/outbreak/",
  "translatedText": "https://meltingasphalt.com/interactive/outbreak/",
  "n_reviews": 0
 },
 {
  "input": "",
  "translatedText": "",
  "n_reviews": 0
 },
 {
  "input": "Excellent visualization of each country's current growth from Minutephysics and Aatish Bhatia:",
  "translatedText": "Excelente visualización del crecimiento actual de cada país de Minutephysics y Aatish Bhatia:",
  "n_reviews": 0
 },
 {
  "input": "https://www.youtube.com/watch?v=54XLXg4fYsc",
  "translatedText": "https://www.youtube.com/watch?v=54XLXg4fYsc",
  "n_reviews": 0
 },
 {
  "input": "",
  "translatedText": "",
  "n_reviews": 0
 },
 {
  "input": "Another good interactive to see what effect various parameters have on the shape of the curve:",
  "translatedText": "Otro buen interactivo para ver qué efecto tienen varios parámetros en la forma de la curva:",
  "n_reviews": 0
 },
 {
  "input": "http://gabgoh.github.io/COVID/index.html",
  "translatedText": "http://gabgoh.github.io/COVID/index.html",
  "n_reviews": 0
 },
 {
  "input": "",
  "translatedText": "",
  "n_reviews": 0
 },
 {
  "input": "If you want to hear a mathematician/epidemiologist's summary of COVID-19, I found this MSRI  talk very worthwhile:",
  "translatedText": "Si desea escuchar el resumen de un matemático/epidemiólogo sobre el COVID-19, esta charla sobre MSRI me pareció muy valiosa:",
  "n_reviews": 0
 },
 {
  "input": "https://youtu.be/MZ957qhzcjI",
  "translatedText": "https://youtu.be/MZ957qhzcjI",
  "n_reviews": 0
 },
 {
  "input": "",
  "translatedText": "",
  "n_reviews": 0
 },
 {
  "input": "Marcel Salathé on Contact Tracing:",
  "translatedText": "Marcel Salathé sobre el rastreo de contactos:",
  "n_reviews": 0
 },
 {
  "input": "https://twitter.com/marcelsalathe/status/1242430736944201730",
  "translatedText": "https://twitter.com/marcelsalathe/status/1242430736944201730",
  "n_reviews": 0
 },
 {
  "input": "",
  "translatedText": "",
  "n_reviews": 0
 },
 {
  "input": "",
  "translatedText": "",
  "n_reviews": 0
 }
]