[
 {
  "input": "The goal is for you to come away from this video understanding one of the most important formulas in all of probability, Bayes' theorem. ",
  "translatedText": "அனைத்து நிகழ்தகவுகளிலும் உள்ள மிக முக்கியமான சூத்திரங்களில் ஒன்றான பேய்ஸின் தேற்றத்தைப் புரிந்துகொண்டு இந்த வீடியோவிலிருந்து நீங்கள் விலகிச் செல்வதே குறிக்கோள். ",
  "model": "google_nmt",
  "n_reviews": 0,
  "start": 0.0,
  "end": 6.84
 },
 {
  "input": "This formula is central to scientific discovery, it's a core tool in machine learning and AI, and it's even been used for treasure hunting, when in the 1980s a small team led by Tommy Thompson, and I'm not making up that name, used Bayesian search tactics to help uncover a ship that had sunk a century and a half earlier, and the ship was carrying what in today's terms amounts to $700 million worth of gold. ",
  "translatedText": "இந்த சூத்திரம் அறிவியல் கண்டுபிடிப்புக்கு மையமானது, இது இயந்திர கற்றல் மற்றும் AI ஆகியவற்றில் ஒரு முக்கிய கருவியாகும், மேலும் இது புதையல் வேட்டைக்கு கூட பயன்படுத்தப்பட்டது, 1980 களில் டாமி தாம்சன் தலைமையிலான ஒரு சிறிய குழு, நான் அந்த பெயரை உருவாக்கவில்லை. ஒன்றரை நூற்றாண்டுக்கு முன்னர் மூழ்கிய கப்பலைக் கண்டறிய உதவும் பேய்சியன் தேடல் உத்திகள், இன்றைய மதிப்பில் $700 மில்லியன் மதிப்புள்ள தங்கத்தை அந்தக் கப்பல் எடுத்துச் சென்றது. ",
  "model": "google_nmt",
  "n_reviews": 0,
  "start": 7.48,
  "end": 30.74
 },
 {
  "input": "So it's a formula worth understanding, but of course there are multiple different levels of possible understanding. ",
  "translatedText": "எனவே இது புரிந்து கொள்ளத் தகுந்த ஒரு சூத்திரம், ஆனால் நிச்சயமாகப் புரிந்துகொள்ளக்கூடிய பல்வேறு நிலைகள் உள்ளன. ",
  "model": "google_nmt",
  "n_reviews": 0,
  "start": 31.34,
  "end": 37.04
 },
 {
  "input": "At the simplest there's just knowing what each one of the parts means, so that you can plug in numbers. ",
  "translatedText": "எளிமையானது, ஒவ்வொரு பகுதியும் எதைக் குறிக்கிறது என்பதைத் தெரிந்துகொள்வதன் மூலம், நீங்கள் எண்களை செருகலாம். ",
  "model": "google_nmt",
  "n_reviews": 0,
  "start": 37.6,
  "end": 42.04
 },
 {
  "input": "Then there's understanding why it's true, and later I'm going to show you a certain diagram that's helpful for rediscovering this formula on the fly as needed. ",
  "translatedText": "அது ஏன் உண்மை என்று புரிந்து கொள்ள முடியும், பின்னர் நான் உங்களுக்கு ஒரு குறிப்பிட்ட வரைபடத்தைக் காண்பிக்கப் போகிறேன், அது தேவைக்கேற்ப பறக்கும்போது இந்த சூத்திரத்தை மீண்டும் கண்டுபிடிப்பதற்கு உதவியாக இருக்கும். ",
  "model": "google_nmt",
  "n_reviews": 0,
  "start": 42.76,
  "end": 50.58
 },
 {
  "input": "But maybe the most important level is being able to recognize when you need to use it. ",
  "translatedText": "ஆனால் மிக முக்கியமான நிலை நீங்கள் எப்போது பயன்படுத்த வேண்டும் என்பதை அடையாளம் காண முடியும். ",
  "model": "google_nmt",
  "n_reviews": 0,
  "start": 51.24,
  "end": 55.54
 },
 {
  "input": "And with the goal of gaining a deeper understanding, you and I are going to tackle these in reverse order. ",
  "translatedText": "மேலும் ஆழமான புரிதலைப் பெறுவதற்கான குறிக்கோளுடன், நீங்களும் நானும் தலைகீழ் வரிசையில் இவற்றைச் சமாளிக்கப் போகிறோம். ",
  "model": "google_nmt",
  "n_reviews": 0,
  "start": 55.54,
  "end": 60.56
 },
 {
  "input": "So before dissecting the formula or explaining the visual that makes it obvious, I'd like to tell you about a man named Steve. ",
  "translatedText": "எனவே சூத்திரத்தைப் பிரிப்பதற்கு முன் அல்லது அதைத் தெளிவாக்கும் காட்சியை விளக்குவதற்கு முன், ஸ்டீவ் என்ற மனிதரைப் பற்றி நான் உங்களுக்குச் சொல்ல விரும்புகிறேன். ",
  "model": "google_nmt",
  "n_reviews": 0,
  "start": 61.02,
  "end": 66.86
 },
 {
  "input": "Listen carefully now. ",
  "translatedText": "இப்போது கவனமாகக் கேளுங்கள். ",
  "model": "google_nmt",
  "n_reviews": 0,
  "start": 67.32,
  "end": 68.72
 },
 {
  "input": "Steve is very shy and withdrawn, invariably helpful but with very little interest in people or the world of reality. ",
  "translatedText": "ஸ்டீவ் மிகவும் வெட்கப்படுபவர் மற்றும் பின்வாங்குபவர், எப்போதும் உதவக்கூடியவர், ஆனால் மக்கள் அல்லது யதார்த்த உலகில் மிகக் குறைந்த அக்கறை கொண்டவர். ",
  "model": "google_nmt",
  "n_reviews": 0,
  "start": 72.74,
  "end": 79.16
 },
 {
  "input": "A meek and tidy soul, he has a need for order and structure, and a passion for detail. ",
  "translatedText": "ஒரு சாந்தமான மற்றும் நேர்த்தியான ஆன்மா, அவருக்கு ஒழுங்கு மற்றும் கட்டமைப்பின் தேவை மற்றும் விவரங்களுக்கான ஆர்வம் உள்ளது. ",
  "model": "google_nmt",
  "n_reviews": 0,
  "start": 79.74,
  "end": 84.1
 },
 {
  "input": "Which of the following do you find more likely? ",
  "translatedText": "பின்வருவனவற்றில் எது அதிக வாய்ப்புள்ளது? ",
  "model": "google_nmt",
  "n_reviews": 0,
  "start": 84.62,
  "end": 86.78
 },
 {
  "input": "Steve is a librarian, or Steve is a farmer? ",
  "translatedText": "ஸ்டீவ் ஒரு நூலகரா, அல்லது ஸ்டீவ் ஒரு விவசாயியா? ",
  "model": "google_nmt",
  "n_reviews": 0,
  "start": 87.2,
  "end": 90.38
 },
 {
  "input": "Some of you may recognize this as an example from a study conducted by the two psychologists Daniel Kahneman and Amos Tversky. ",
  "translatedText": "டேனியல் கான்மேன் மற்றும் அமோஸ் ட்வெர்ஸ்கி ஆகிய இரு உளவியலாளர்களால் நடத்தப்பட்ட ஒரு ஆய்வில் இருந்து உங்களில் சிலர் இதை ஒரு எடுத்துக்காட்டு என்று அடையாளம் காணலாம். ",
  "model": "google_nmt",
  "n_reviews": 0,
  "start": 91.4,
  "end": 97.44
 },
 {
  "input": "Their work was a big deal, it won a Nobel Prize, and it's been popularized many times over in books like Kahneman's Thinking Fast and Slow, or Michael Lewis's The Undoing Project. ",
  "translatedText": "அவர்களின் பணி ஒரு பெரிய விஷயமாக இருந்தது, அது நோபல் பரிசை வென்றது, மேலும் இது கான்மேனின் திங்கிங் ஃபாஸ்ட் அண்ட் ஸ்லோ, அல்லது மைக்கேல் லூயிஸின் தி அன்டூயிங் ப்ராஜெக்ட் போன்ற புத்தகங்களில் பலமுறை பிரபலப்படுத்தப்பட்டது. ",
  "model": "google_nmt",
  "n_reviews": 0,
  "start": 98.2,
  "end": 106.56
 },
 {
  "input": "What they researched was human judgments, with a frequent focus on when these judgments irrationally contradict what the laws of probability suggest they should be. ",
  "translatedText": "அவர்கள் ஆராய்ச்சி செய்தது மனித தீர்ப்புகள், இந்த தீர்ப்புகள் பகுத்தறிவற்ற முறையில் முரண்படும் போது, நிகழ்தகவு விதிகள் என்னவாக இருக்க வேண்டும் என்று அடிக்கடி கவனம் செலுத்துகின்றன. ",
  "model": "google_nmt",
  "n_reviews": 0,
  "start": 107.42,
  "end": 115.78
 },
 {
  "input": "The example with Steve, our maybe librarian, maybe farmer, illustrates one specific type of irrationality, or maybe I should say alleged irrationality, there are people who debate the conclusion here, but more on that later on. ",
  "translatedText": "ஸ்டீவ் உடனான உதாரணம், நமது நூலகர், ஒருவேளை விவசாயி, ஒரு குறிப்பிட்ட வகை பகுத்தறிவின்மையை விளக்குகிறது, அல்லது நான் கூறப்படும் பகுத்தறிவின்மை என்று கூறலாம், இங்கே முடிவைப் பற்றி விவாதிப்பவர்கள் உள்ளனர், ஆனால் அதைப் பற்றி பின்னர் மேலும். ",
  "model": "google_nmt",
  "n_reviews": 0,
  "start": 116.34,
  "end": 129.62
 },
 {
  "input": "According to Kahneman and Tversky, after people are given this description of Steve as a meek and tidy soul, most say he's more likely to be a librarian. ",
  "translatedText": "கான்மேன் மற்றும் ட்வெர்ஸ்கியின் கூற்றுப்படி, ஸ்டீவ் ஒரு சாந்தமான மற்றும் நேர்த்தியான ஆன்மா என்று மக்களுக்கு இந்த விளக்கத்தை அளித்த பிறகு, அவர் ஒரு நூலகராக இருப்பதற்கான வாய்ப்புகள் அதிகம் என்று பெரும்பாலானவர்கள் கூறுகிறார்கள். ",
  "model": "google_nmt",
  "n_reviews": 0,
  "start": 129.98,
  "end": 138.0
 },
 {
  "input": "After all, these traits line up better with the stereotypical view of a librarian than a farmer. ",
  "translatedText": "எல்லாவற்றிற்கும் மேலாக, இந்த குணாதிசயங்கள் ஒரு விவசாயியை விட ஒரு நூலகரின் ஒரே மாதிரியான பார்வையுடன் சிறப்பாக வரிசைப்படுத்தப்படுகின்றன. ",
  "model": "google_nmt",
  "n_reviews": 0,
  "start": 138.0,
  "end": 143.46
 },
 {
  "input": "And according to Kahneman and Tversky, this is irrational. ",
  "translatedText": "கான்மேன் மற்றும் ட்வெர்ஸ்கியின் கூற்றுப்படி, இது பகுத்தறிவற்றது. ",
  "model": "google_nmt",
  "n_reviews": 0,
  "start": 144.2,
  "end": 146.88
 },
 {
  "input": "The point is not whether people hold correct or biased views about the personalities of librarians and farmers, it's that almost nobody thinks to incorporate information about the ratio of farmers to librarians in their judgments. ",
  "translatedText": "நூலகர்கள் மற்றும் விவசாயிகளின் ஆளுமைகளைப் பற்றி மக்கள் சரியான அல்லது பக்கச்சார்பான கருத்துக்களைக் கொண்டிருக்கிறார்களா என்பது முக்கியமல்ல, விவசாயிகள் மற்றும் நூலகர்களின் விகிதம் பற்றிய தகவல்களை யாரும் தங்கள் தீர்ப்புகளில் இணைக்க நினைக்கவில்லை. ",
  "model": "google_nmt",
  "n_reviews": 0,
  "start": 147.6,
  "end": 160.24
 },
 {
  "input": "In their paper, Kahneman and Tversky said that in the US, that ratio is about 20 to 1. ",
  "translatedText": "கான்மேன் மற்றும் ட்வெர்ஸ்கி ஆகியோர் தங்கள் ஆய்வறிக்கையில், அமெரிக்காவில் அந்த விகிதம் 20 முதல் 1 வரை உள்ளது என்று கூறியுள்ளனர். ",
  "model": "google_nmt",
  "n_reviews": 0,
  "start": 160.92,
  "end": 165.18
 },
 {
  "input": "The numbers I could find today put that much higher, but let's stick with the 20 to 1 number, since it's a little easier to illustrate and proves the point as well. ",
  "translatedText": "இன்று நான் கண்டுபிடிக்கக்கூடிய எண்கள் அதைவிட அதிகமாக உள்ளன, ஆனால் 20 முதல் 1 எண்ணுடன் ஒட்டிக்கொள்வோம், ஏனெனில் இது விளக்குவது கொஞ்சம் எளிதானது மற்றும் புள்ளியையும் நிரூபிக்கிறது. ",
  "model": "google_nmt",
  "n_reviews": 0,
  "start": 165.58,
  "end": 173.42
 },
 {
  "input": "To be clear, anyone who is asked this question is not expected to have perfect information about the actual statistics of farmers and librarians and their personality traits. ",
  "translatedText": "தெளிவாகச் சொல்வதென்றால், இந்தக் கேள்வியைக் கேட்கும் எவருக்கும் விவசாயிகள் மற்றும் நூலகர்களின் உண்மையான புள்ளிவிவரங்கள் மற்றும் அவர்களின் ஆளுமைப் பண்புகள் பற்றிய சரியான தகவல்கள் இருக்கும் என்று எதிர்பார்க்கப்படுவதில்லை. ",
  "model": "google_nmt",
  "n_reviews": 0,
  "start": 174.28,
  "end": 183.14
 },
 {
  "input": "But the question is whether people even think to consider that ratio enough to at least make a rough estimate. ",
  "translatedText": "ஆனால், அந்த விகிதத்தை குறைந்தபட்சம் தோராயமான மதிப்பீட்டையாவது செய்ய மக்கள் நினைக்கிறார்களா என்பதுதான் கேள்வி. ",
  "model": "google_nmt",
  "n_reviews": 0,
  "start": 183.68,
  "end": 189.22
 },
 {
  "input": "Rationality is not about knowing facts, it's about recognizing which facts are relevant. ",
  "translatedText": "பகுத்தறிவு என்பது உண்மைகளை அறிவது அல்ல, எந்த உண்மைகள் பொருத்தமானவை என்பதை அங்கீகரிப்பதுதான். ",
  "model": "google_nmt",
  "n_reviews": 0,
  "start": 190.04,
  "end": 194.46
 },
 {
  "input": "Now if you do think to make that estimate, there's a pretty simple way to reason about the question, which, spoiler alert, involves all of the essential reasoning behind Bayes' theorem. ",
  "translatedText": "இப்போது அந்த மதிப்பீட்டைச் செய்ய நீங்கள் நினைத்தால், கேள்வியைப் பற்றி நியாயப்படுத்த ஒரு அழகான எளிய வழி உள்ளது, இது, ஸ்பாய்லர் எச்சரிக்கை, பேய்ஸின் தேற்றத்திற்குப் பின்னால் உள்ள அனைத்து அத்தியாவசிய காரணங்களையும் உள்ளடக்கியது. ",
  "model": "google_nmt",
  "n_reviews": 0,
  "start": 195.88,
  "end": 203.9
 },
 {
  "input": "You might start by picturing a representative sample of farmers and librarians, say 200 farmers and 10 librarians. ",
  "translatedText": "200 விவசாயிகள் மற்றும் 10 நூலகர்கள் கூறும் விவசாயிகள் மற்றும் நூலகர்களின் பிரதிநிதி மாதிரியைப் படம்பிடிப்பதன் மூலம் நீங்கள் தொடங்கலாம். ",
  "model": "google_nmt",
  "n_reviews": 0,
  "start": 204.66,
  "end": 211.02
 },
 {
  "input": "Then when you hear of this meek and tidy soul description, let's say that your gut instinct is that 40% of librarians would fit that description, and that 10% of farmers would. ",
  "translatedText": "இந்த சாந்தமான மற்றும் நேர்த்தியான ஆன்மா விளக்கத்தை நீங்கள் கேட்கும்போது, 40% நூலகர்கள் அந்த விளக்கத்தைப் பொருத்துவார்கள், 10% விவசாயிகள் அதைப் பொருத்துவார்கள் என்பது உங்கள் உள்ளுணர்வு என்று சொல்லலாம். ",
  "model": "google_nmt",
  "n_reviews": 0,
  "start": 211.74,
  "end": 221.36
 },
 {
  "input": "If those are your estimates, it would mean that from your sample you would expect about 4 librarians to fit the description, and about 20 farmers to fit that description. ",
  "translatedText": "அவை உங்களின் மதிப்பீடுகளாக இருந்தால், உங்கள் மாதிரியில் இருந்து 4 நூலகர்கள் விளக்கத்துடன் பொருந்துவார்கள் என்றும், அந்த விளக்கத்திற்கு சுமார் 20 விவசாயிகள் பொருந்துவார்கள் என்றும் நீங்கள் எதிர்பார்க்கலாம். ",
  "model": "google_nmt",
  "n_reviews": 0,
  "start": 222.02,
  "end": 230.24
 },
 {
  "input": "So the probability that a random person among those who fit this description is a librarian is 4 out of 24, or 16.7%. ",
  "translatedText": "எனவே இந்த விளக்கத்திற்குப் பொருந்தியவர்களில் ஒரு சீரற்ற நபர் நூலகராக இருப்பதற்கான நிகழ்தகவு 24 இல் 4 அல்லது 16 ஆகும். ",
  "model": "google_nmt",
  "n_reviews": 0,
  "start": 231.02,
  "end": 240.1
 },
 {
  "input": "So even if you think that a librarian is 4 times as likely as a farmer to fit this description, that's not enough to overcome the fact that there are way more farmers. ",
  "translatedText": "7% எனவே, நூலகர் ஒரு விவசாயியை விட 4 மடங்கு இந்த விளக்கத்தைப் பொருத்துவார் என்று நீங்கள் நினைத்தாலும் கூட, அதிக விவசாயிகள் உள்ளனர் என்ற உண்மையைக் கடக்க அது போதாது. ",
  "model": "google_nmt",
  "n_reviews": 0,
  "start": 240.1,
  "end": 249.02
 },
 {
  "input": "The upshot, and this is the key mantra underlying Bayes' theorem, is that new evidence does not completely determine your beliefs in a vacuum, it should update prior beliefs. ",
  "translatedText": "விளைவு, மற்றும் இது பேய்ஸ் தேற்றத்தின் அடிப்படையிலான முக்கிய மந்திரமாகும், புதிய சான்றுகள் வெற்றிடத்தில் உங்கள் நம்பிக்கைகளை முழுமையாக தீர்மானிக்கவில்லை, அது முந்தைய நம்பிக்கைகளை புதுப்பிக்க வேண்டும். ",
  "model": "google_nmt",
  "n_reviews": 0,
  "start": 249.72,
  "end": 259.22
 },
 {
  "input": "If this line of reasoning makes sense to you, the way that seeing evidence restricts the space of possibilities and the ratio you need to consider after that, then congratulations, you understand the heart of Bayes' theorem. ",
  "translatedText": "இந்த பகுத்தறிவு வரி உங்களுக்குப் புரியுமானால், ஆதாரங்களைப் பார்ப்பது சாத்தியக்கூறுகளின் இடத்தையும் அதன் பிறகு நீங்கள் கருத்தில் கொள்ள வேண்டிய விகிதத்தையும் கட்டுப்படுத்துகிறது என்றால், வாழ்த்துக்கள், பேய்ஸின் தேற்றத்தின் இதயத்தை நீங்கள் புரிந்துகொள்கிறீர்கள். ",
  "model": "google_nmt",
  "n_reviews": 0,
  "start": 261.12,
  "end": 272.36
 },
 {
  "input": "Maybe the numbers you would estimate would be a little different, but what matters is how you fit the numbers together to update your beliefs based on evidence. ",
  "translatedText": "ஒருவேளை நீங்கள் மதிப்பிடும் எண்கள் சற்று வித்தியாசமாக இருக்கலாம், ஆனால் ஆதாரங்களின் அடிப்படையில் உங்கள் நம்பிக்கைகளைப் புதுப்பிக்க எண்களை எவ்வாறு ஒன்றாகப் பொருத்துகிறீர்கள் என்பதுதான் முக்கியம். ",
  "model": "google_nmt",
  "n_reviews": 0,
  "start": 272.36,
  "end": 280.6
 },
 {
  "input": "Understanding one example is one thing, but see if you can take a minute to generalize everything we just did and write it all down as a formula. ",
  "translatedText": "ஒரு உதாரணத்தைப் புரிந்துகொள்வது ஒன்றுதான், ஆனால் நாங்கள் செய்த அனைத்தையும் பொதுமைப்படுத்த ஒரு நிமிடம் ஒதுக்கி, அனைத்தையும் ஒரு சூத்திரமாக எழுத முடியுமா என்று பாருங்கள். ",
  "model": "google_nmt",
  "n_reviews": 0,
  "start": 282.08,
  "end": 289.74
 },
 {
  "input": "The general situation where Bayes' theorem is relevant is when you have some hypothesis, like Steve is a librarian, and you see some new evidence, say this verbal description of Steve as a meek and tidy soul. ",
  "translatedText": "பேய்ஸின் தேற்றம் பொருத்தமானதாக இருக்கும் பொதுவான சூழ்நிலை என்னவென்றால், ஸ்டீவ் ஒரு நூலகர் என்பது போன்ற சில கருதுகோள்களை நீங்கள் வைத்திருக்கிறீர்கள், மேலும் சில புதிய ஆதாரங்களை நீங்கள் பார்க்கிறீர்கள், ஸ்டீவ் ஒரு சாந்தமான மற்றும் நேர்த்தியான ஆத்மா என்று சொல்லுங்கள். ",
  "model": "google_nmt",
  "n_reviews": 0,
  "start": 292.32,
  "end": 303.98
 },
 {
  "input": "You want to know the probability that your hypothesis holds given that the evidence is true. ",
  "translatedText": "ஆதாரம் உண்மை என்று உங்கள் கருதுகோள் வைத்திருக்கும் நிகழ்தகவை நீங்கள் அறிய விரும்புகிறீர்கள். ",
  "model": "google_nmt",
  "n_reviews": 0,
  "start": 304.38,
  "end": 309.64
 },
 {
  "input": "In the standard notation, this vertical bar means given that, as in we're restricting our view only to the possibilities where the evidence holds. ",
  "translatedText": "நிலையான குறியீட்டில், இந்த செங்குத்து பட்டை என்பது, ஆதாரம் உள்ள சாத்தியக்கூறுகளுக்கு மட்டுமே நாம் நமது பார்வையை கட்டுப்படுத்துகிறோம். ",
  "model": "google_nmt",
  "n_reviews": 0,
  "start": 310.44,
  "end": 318.96
 },
 {
  "input": "Remember the first relevant number we used, the probability that the hypothesis holds before considering any of that new evidence. ",
  "translatedText": "நாங்கள் பயன்படுத்திய முதல் தொடர்புடைய எண்ணை நினைவில் கொள்ளுங்கள், அந்த புதிய சான்றுகளில் ஏதேனும் ஒன்றைக் கருத்தில் கொள்வதற்கு முன் கருதுகோள் வைத்திருக்கும் நிகழ்தகவு. ",
  "model": "google_nmt",
  "n_reviews": 0,
  "start": 320.22,
  "end": 327.34
 },
 {
  "input": "In our example, that was 1 out of 21, and it came from considering the ratio of librarians to farmers in the general population. ",
  "translatedText": "எங்கள் எடுத்துக்காட்டில், அது 21 இல் 1 ஆகும், மேலும் இது பொது மக்களில் விவசாயிகளுக்கும் நூலகர்களுக்கும் உள்ள விகிதத்தைக் கருத்தில் கொண்டு வந்தது. ",
  "model": "google_nmt",
  "n_reviews": 0,
  "start": 327.72,
  "end": 334.64
 },
 {
  "input": "This number is known as the prior. ",
  "translatedText": "இந்த எண் முந்தைய எண் என்று அழைக்கப்படுகிறது. ",
  "model": "google_nmt",
  "n_reviews": 0,
  "start": 335.52,
  "end": 336.98
 },
 {
  "input": "After that, we need to consider the proportion of librarians that fit this description, the probability that we would see the evidence given that the hypothesis is true. ",
  "translatedText": "அதன் பிறகு, இந்த விளக்கத்திற்கு பொருந்தக்கூடிய நூலகர்களின் விகிதாச்சாரத்தை நாம் கருத்தில் கொள்ள வேண்டும், கருதுகோள் உண்மையானது என்பதற்கான ஆதாரங்களை நாம் காண்பதற்கான நிகழ்தகவு. ",
  "model": "google_nmt",
  "n_reviews": 0,
  "start": 338.02,
  "end": 347.3
 },
 {
  "input": "Again, when you see this vertical bar, it means we're talking about some proportion of a limited part of the total space of possibilities. ",
  "translatedText": "மீண்டும், நீங்கள் இந்த செங்குத்து பட்டியைப் பார்க்கும்போது, மொத்த சாத்தியக்கூறுகளின் குறிப்பிட்ட பகுதியின் சில விகிதத்தைப் பற்றி பேசுகிறோம் என்று அர்த்தம். ",
  "model": "google_nmt",
  "n_reviews": 0,
  "start": 348.1,
  "end": 354.84
 },
 {
  "input": "In this case, that limited part is the left side, where the hypothesis holds. ",
  "translatedText": "இந்த வழக்கில், அந்த வரையறுக்கப்பட்ட பகுதி இடது பக்கமாகும், அங்கு கருதுகோள் உள்ளது. ",
  "model": "google_nmt",
  "n_reviews": 0,
  "start": 355.32,
  "end": 359.3
 },
 {
  "input": "In the context of Bayes' theorem, this value also has a special name, it's called the likelihood. ",
  "translatedText": "பேய்ஸ் தேற்றத்தின் பின்னணியில், இந்த மதிப்புக்கு ஒரு சிறப்புப் பெயரும் உள்ளது, இது நிகழ்தகவு என்று அழைக்கப்படுகிறது. ",
  "model": "google_nmt",
  "n_reviews": 0,
  "start": 359.96,
  "end": 364.64
 },
 {
  "input": "Similarly, you need to know how much of the other side of the space includes the evidence, the probability of seeing the evidence given that the hypothesis isn't true. ",
  "translatedText": "இதேபோல், இடத்தின் மறுபக்கம் எவ்வளவு ஆதாரங்களை உள்ளடக்கியது என்பதை நீங்கள் தெரிந்து கொள்ள வேண்டும், கருதுகோள் உண்மையல்ல என்று கொடுக்கப்பட்ட ஆதாரங்களைப் பார்ப்பதற்கான நிகழ்தகவு. ",
  "model": "google_nmt",
  "n_reviews": 0,
  "start": 365.7,
  "end": 373.56
 },
 {
  "input": "This funny little elbow symbol is commonly used in probability to mean not. ",
  "translatedText": "இந்த வேடிக்கையான சிறிய முழங்கை சின்னம் பொதுவாக இல்லை என்று பொருள்பட நிகழ்தகவில் பயன்படுத்தப்படுகிறது. ",
  "model": "google_nmt",
  "n_reviews": 0,
  "start": 374.34,
  "end": 378.42
 },
 {
  "input": "So, with the notation in place, remember what our final answer was. ",
  "translatedText": "எனவே, குறியிடப்பட்ட இடத்தில், எங்கள் இறுதி பதில் என்ன என்பதை நினைவில் கொள்ளுங்கள். ",
  "model": "google_nmt",
  "n_reviews": 0,
  "start": 379.86,
  "end": 383.02
 },
 {
  "input": "The probability that our librarian hypothesis is true given the evidence is the total number of librarians fitting the evidence, 4, divided by the total number of people fitting the evidence, 24. ",
  "translatedText": "நமது நூலகக் கருதுகோள் ஆதாரத்துடன் உண்மையாக இருப்பதற்கான நிகழ்தகவு, ஆதாரங்களைப் பொருத்தும் மொத்த நூலகர்களின் எண்ணிக்கை, 4, ஆதாரங்களைப் பொருத்தும் மொத்த நபர்களின் எண்ணிக்கை, 24. ",
  "model": "google_nmt",
  "n_reviews": 0,
  "start": 383.36,
  "end": 394.88
 },
 {
  "input": "But where did that 4 come from? ",
  "translatedText": "ஆனால் அந்த 4 எங்கிருந்து வந்தது? ",
  "model": "google_nmt",
  "n_reviews": 0,
  "start": 395.76,
  "end": 397.18
 },
 {
  "input": "Well, it's the total number of people, times the prior probability of being a librarian, giving us the 10 total librarians, times the probability that one of those fits the evidence. ",
  "translatedText": "சரி, இது மொத்த நபர்களின் எண்ணிக்கை, ஒரு நூலகராக இருப்பதற்கான முந்தைய நிகழ்தகவைக் காட்டிலும், 10 மொத்த நூலகர்களை நமக்குத் தருகிறது. ",
  "model": "google_nmt",
  "n_reviews": 0,
  "start": 397.84,
  "end": 408.42
 },
 {
  "input": "That same number shows up again in the denominator, but we need to add in the rest, the total number of people times the proportion who are not librarians, times the proportion of those who fit the evidence, which in our example gives 20. ",
  "translatedText": "அதே எண் மீண்டும் வகுப்பில் காட்டப்படும், ஆனால் மீதமுள்ள எண்ணிக்கையில் நாம் சேர்க்க வேண்டும், மொத்த நபர்களின் எண்ணிக்கையை நூலகர்கள் அல்லாத விகிதாச்சாரத்தின் மடங்குகள், ஆதாரங்களுடன் பொருந்தியவர்களின் விகிதம், இது எங்கள் எடுத்துக்காட்டில் 20 ஐ அளிக்கிறது. ",
  "model": "google_nmt",
  "n_reviews": 0,
  "start": 409.22,
  "end": 422.14
 },
 {
  "input": "Now notice the total number of people here, 210, that gets cancelled out, and of course it should, that was just an arbitrary choice made for the sake of illustration. ",
  "translatedText": "இப்போது இங்குள்ள மொத்த நபர்களின் எண்ணிக்கை, 210, ரத்து செய்யப்படுவதைக் கவனியுங்கள், நிச்சயமாக அது, விளக்கத்திற்காக செய்யப்பட்ட தன்னிச்சையான தேர்வாகும். ",
  "model": "google_nmt",
  "n_reviews": 0,
  "start": 423.22,
  "end": 431.04
 },
 {
  "input": "This leaves us finally with a more abstract representation purely in terms of probabilities, and this, my friends, is Bayes' theorem. ",
  "translatedText": "இது இறுதியாக நிகழ்தகவுகளின் அடிப்படையில் மிகவும் சுருக்கமான பிரதிநிதித்துவத்தை நமக்கு விட்டுச் செல்கிறது, மேலும் இது பேய்ஸின் தேற்றமாகும். ",
  "model": "google_nmt",
  "n_reviews": 0,
  "start": 431.62,
  "end": 439.22
 },
 {
  "input": "More often, you see this denominator written simply as P of E, the total probability of seeing the evidence, which in our example would be the 24 out of 210. ",
  "translatedText": "பெரும்பாலும், இந்த வகுப்பினை P இன் E என எழுதப்பட்டிருப்பதை நீங்கள் காண்கிறீர்கள், ஆதாரங்களைப் பார்ப்பதற்கான மொத்த நிகழ்தகவு, இது எங்கள் எடுத்துக்காட்டில் 210 இல் 24 ஆக இருக்கும். ",
  "model": "google_nmt",
  "n_reviews": 0,
  "start": 440.42,
  "end": 450.46
 },
 {
  "input": "But in practice, to calculate it, you almost always have to break it down into the case where the hypothesis is true, and the one where it isn't. ",
  "translatedText": "ஆனால் நடைமுறையில், அதைக் கணக்கிட, நீங்கள் எப்பொழுதும் கருதுகோள் உண்மையாக இருக்கும், மற்றும் அது இல்லாத நிலையில் அதை உடைக்க வேண்டும். ",
  "model": "google_nmt",
  "n_reviews": 0,
  "start": 451.12,
  "end": 458.8
 },
 {
  "input": "Capping things off with one final bit of jargon, this answer is called the posterior, it's your belief about the hypothesis after seeing the evidence. ",
  "translatedText": "ஒரு இறுதிப் வாசகத்தின் மூலம் விஷயங்களை மூடுவது, இந்த பதில் பின்புறம் என்று அழைக்கப்படுகிறது, இது ஆதாரங்களைப் பார்த்த பிறகு கருதுகோள் பற்றிய உங்கள் நம்பிக்கை. ",
  "model": "google_nmt",
  "n_reviews": 0,
  "start": 460.06,
  "end": 468.6
 },
 {
  "input": "Writing it out abstractly might seem more complicated than just thinking through the example directly with a representative sample. ",
  "translatedText": "ஒரு பிரதிநிதி மாதிரியுடன் நேரடியாக எடுத்துக்காட்டைப் பற்றி சிந்திப்பதை விட சுருக்கமாக எழுதுவது மிகவும் சிக்கலானதாகத் தோன்றலாம். ",
  "model": "google_nmt",
  "n_reviews": 0,
  "start": 470.16,
  "end": 476.5
 },
 {
  "input": "And yeah, it is. ",
  "translatedText": "ஆம், அது. ",
  "model": "google_nmt",
  "n_reviews": 0,
  "start": 476.92,
  "end": 478.78
 },
 {
  "input": "Keep in mind though, the value of a formula like this is that it lets you quantify and systematize the idea of changing beliefs. ",
  "translatedText": "இருப்பினும், இதுபோன்ற ஒரு சூத்திரத்தின் மதிப்பு என்னவென்றால், நம்பிக்கைகளை மாற்றுவதற்கான யோசனையை அளவிடவும் முறைப்படுத்தவும் இது உங்களை அனுமதிக்கிறது. ",
  "model": "google_nmt",
  "n_reviews": 0,
  "start": 479.2,
  "end": 486.26
 },
 {
  "input": "Scientists use this formula when they're analyzing the extent to which new data validates or invalidates their models. ",
  "translatedText": "புதிய தரவு எந்த அளவிற்கு அவர்களின் மாதிரிகளை சரிபார்க்கிறது அல்லது செல்லாததாக்குகிறது என்பதை ஆய்வு செய்யும் போது விஞ்ஞானிகள் இந்த சூத்திரத்தைப் பயன்படுத்துகின்றனர். ",
  "model": "google_nmt",
  "n_reviews": 0,
  "start": 486.94,
  "end": 492.84
 },
 {
  "input": "Programmers will sometimes use it in building artificial intelligence, where at times you want to explicitly and numerically model a machine's belief. ",
  "translatedText": "புரோகிராமர்கள் சில நேரங்களில் செயற்கை நுண்ணறிவை உருவாக்குவதில் இதைப் பயன்படுத்துவார்கள், சில சமயங்களில் நீங்கள் இயந்திரத்தின் நம்பிக்கையை வெளிப்படையாகவும் எண்ணியல் ரீதியாகவும் வடிவமைக்க விரும்புகிறீர்கள். ",
  "model": "google_nmt",
  "n_reviews": 0,
  "start": 492.84,
  "end": 500.64
 },
 {
  "input": "And honestly, just for the way you view yourself and your own opinions and what it takes for your mind to change, Bayes' theorem has a way of reframing how you even think about thought itself. ",
  "translatedText": "மேலும் நேர்மையாக, உங்களையும் உங்கள் சொந்தக் கருத்துக்களையும் நீங்கள் பார்க்கும் விதம் மற்றும் உங்கள் மனம் மாறுவதற்கு என்ன தேவை என்பதைப் பொறுத்து, பேய்ஸின் தேற்றம், நீங்கள் சிந்தனையைப் பற்றி எப்படி நினைக்கிறீர்கள் என்பதை மறுபரிசீலனை செய்யும் ஒரு வழியைக் கொண்டுள்ளது. ",
  "model": "google_nmt",
  "n_reviews": 0,
  "start": 501.4,
  "end": 510.82
 },
 {
  "input": "Putting a formula to it can also be more important as the examples get more and more intricate. ",
  "translatedText": "எடுத்துக்காட்டுகள் மேலும் மேலும் சிக்கலானதாக இருப்பதால் அதற்கு ஒரு சூத்திரத்தை வைப்பது மிகவும் முக்கியமானது. ",
  "model": "google_nmt",
  "n_reviews": 0,
  "start": 512.3,
  "end": 516.34
 },
 {
  "input": "However you write it, I actually encourage you not to try memorizing the formula, but to instead draw out this diagram as needed. ",
  "translatedText": "நீங்கள் எப்படி எழுதினாலும், சூத்திரத்தை மனப்பாடம் செய்ய முயற்சிக்க வேண்டாம், மாறாக இந்த வரைபடத்தை தேவைக்கேற்ப வரையுமாறு நான் உங்களை ஊக்குவிக்கிறேன். ",
  "model": "google_nmt",
  "n_reviews": 0,
  "start": 517.08,
  "end": 524.68
 },
 {
  "input": "It's sort of a distilled version of thinking with a representative sample, where we think with areas instead of counts, which is more flexible and easier to sketch on the fly. ",
  "translatedText": "இது ஒரு பிரதிநிதி மாதிரியுடன் சிந்திக்கும் ஒரு வடிகட்டப்பட்ட பதிப்பாகும், அங்கு எண்ணிக்கைகளுக்குப் பதிலாக பகுதிகளைக் கொண்டு சிந்திக்கிறோம், இது மிகவும் நெகிழ்வானது மற்றும் பறக்கும்போது வரைவதற்கு எளிதானது. ",
  "model": "google_nmt",
  "n_reviews": 0,
  "start": 525.26,
  "end": 533.62
 },
 {
  "input": "Rather than bringing to mind some specific number of examples, like 210, think of the space of all possibilities as a 1x1 square. ",
  "translatedText": "210 போன்ற சில குறிப்பிட்ட எண்ணிக்கையிலான எடுத்துக்காட்டுகளை மனதில் கொண்டு வருவதற்குப் பதிலாக, எல்லா சாத்தியக்கூறுகளின் இடத்தையும் 1x1 சதுரமாகக் கருதுங்கள். ",
  "model": "google_nmt",
  "n_reviews": 0,
  "start": 534.26,
  "end": 541.38
 },
 {
  "input": "Then any event occupies some subset of this space, and the probability of that event can be thought about as the area of that subset. ",
  "translatedText": "எந்த நிகழ்வும் இந்த இடத்தின் சில துணைக்குழுக்களை ஆக்கிரமித்துள்ளது, மேலும் அந்த நிகழ்வின் நிகழ்தகவை அந்த துணைக்குழுவின் பரப்பளவில் கருதலாம். ",
  "model": "google_nmt",
  "n_reviews": 0,
  "start": 542.12,
  "end": 550.94
 },
 {
  "input": "For example, I like to think of the hypothesis as living in the left part of the square with a width of p of h. ",
  "translatedText": "எடுத்துக்காட்டாக, h இன் அகலத்துடன் சதுரத்தின் இடது பகுதியில் வாழும் கருதுகோளை நான் நினைக்க விரும்புகிறேன். ",
  "model": "google_nmt",
  "n_reviews": 0,
  "start": 551.54,
  "end": 557.66
 },
 {
  "input": "I recognize I'm being a bit repetitive, but when you see evidence, the space of possibilities gets restricted, and the crucial part is that restriction might not be even between the left and the right, so the new probability for the hypothesis is the proportion it occupies in this restricted wonky shape. ",
  "translatedText": "நான் சற்றுத் திரும்பத் திரும்பச் சொல்கிறேன் என்பதை நான் அடையாளம் காண்கிறேன், ஆனால் நீங்கள் ஆதாரங்களைப் பார்க்கும்போது, சாத்தியக்கூறுகளின் இடைவெளி கட்டுப்படுத்தப்படுகிறது, மேலும் முக்கியமான பகுதி என்னவென்றால், கட்டுப்பாடு இடது மற்றும் வலது இடையே கூட இருக்காது, எனவே கருதுகோளின் புதிய நிகழ்தகவு இந்த தடைசெய்யப்பட்ட வன்கி வடிவத்தில் அது ஆக்கிரமித்துள்ள விகிதம். ",
  "model": "google_nmt",
  "n_reviews": 0,
  "start": 558.32,
  "end": 576.94
 },
 {
  "input": "Now if you think a farmer is just as likely to fit the evidence as a librarian, then the proportion doesn't change, which should make sense, right? ",
  "translatedText": "இப்போது நீங்கள் ஒரு விவசாயிக்கு நூலகர் போன்ற சான்றுகள் பொருந்தக்கூடும் என்று நீங்கள் நினைத்தால், விகிதாச்சாரம் மாறாது, அது அர்த்தமுள்ளதாக இருக்க வேண்டும், இல்லையா? ",
  "model": "google_nmt",
  "n_reviews": 0,
  "start": 577.64,
  "end": 586.24
 },
 {
  "input": "And evidence doesn't change your beliefs. ",
  "translatedText": "ஆதாரங்கள் உங்கள் நம்பிக்கைகளை மாற்றாது. ",
  "model": "google_nmt",
  "n_reviews": 0,
  "start": 586.26,
  "end": 588.32
 },
 {
  "input": "But when these likelihoods are very different from each other, that's when your belief changes a lot. ",
  "translatedText": "ஆனால் இந்த சாத்தியக்கூறுகள் ஒன்றுக்கொன்று வித்தியாசமாக இருக்கும்போது, உங்கள் நம்பிக்கை நிறைய மாறுகிறது. ",
  "model": "google_nmt",
  "n_reviews": 0,
  "start": 588.9,
  "end": 593.48
 },
 {
  "input": "Bayes' theorem spells out what that proportion is, and if you want you can read it geometrically. ",
  "translatedText": "பேய்ஸின் தேற்றம் அந்த விகிதாச்சாரத்தை விவரிக்கிறது, நீங்கள் விரும்பினால் அதை வடிவியல் முறையில் படிக்கலாம். ",
  "model": "google_nmt",
  "n_reviews": 0,
  "start": 595.76,
  "end": 600.52
 },
 {
  "input": "Something like p of h times p of e given h, the probability of both the hypothesis and the evidence occurring together, is the width times the height of this little left rectangle, the area of that region. ",
  "translatedText": "h கொடுக்கப்பட்ட e இன் p இன் h மடங்கு p போன்றது, கருதுகோள் மற்றும் சான்றுகள் இரண்டின் நிகழ்தகவு, இந்த சிறிய இடது செவ்வகத்தின் உயரத்தின் அகலம், அந்தப் பகுதியின் பரப்பளவு. ",
  "model": "google_nmt",
  "n_reviews": 0,
  "start": 600.9,
  "end": 613.08
 },
 {
  "input": "Alright, this is probably a good time to take a step back and consider a few of the broader takeaways about how to make probability more intuitive, beyond Bayes' theorem. ",
  "translatedText": "சரி, பேய்ஸ் தேற்றத்திற்கு அப்பால், நிகழ்தகவை எப்படி மிகவும் உள்ளுணர்வாக மாற்றுவது என்பது பற்றிய சில விரிவான விஷயங்களைக் கருத்தில் கொள்ள இது ஒரு நல்ல நேரம். ",
  "model": "google_nmt",
  "n_reviews": 0,
  "start": 614.76,
  "end": 623.22
 },
 {
  "input": "First off, notice how the trick of thinking about a representative sample with some specific number of people, like our 210 librarians and farmers, was really helpful. ",
  "translatedText": "முதலில், எங்களின் 210 நூலகர்கள் மற்றும் விவசாயிகள் போன்ற குறிப்பிட்ட எண்ணிக்கையிலான நபர்களுடன் பிரதிநிதித்துவ மாதிரியைப் பற்றி சிந்திக்கும் தந்திரம் உண்மையில் எவ்வாறு பயனுள்ளதாக இருந்தது என்பதைக் கவனியுங்கள். ",
  "model": "google_nmt",
  "n_reviews": 0,
  "start": 623.78,
  "end": 632.4
 },
 {
  "input": "There's actually another Kahneman and Tversky result which is all about this, and it's interesting enough to interject here. ",
  "translatedText": "உண்மையில் மற்றொரு கான்மேன் மற்றும் ட்வெர்ஸ்கி முடிவு உள்ளது, இது இதைப் பற்றியது, மேலும் இங்கே குறுக்கிடும் அளவுக்கு சுவாரஸ்யமானது. ",
  "model": "google_nmt",
  "n_reviews": 0,
  "start": 632.96,
  "end": 638.38
 },
 {
  "input": "They did this experiment that was similar to the one with Steve, but where people were given the following description of a fictitious woman named Linda. ",
  "translatedText": "அவர்கள் இந்த பரிசோதனையை ஸ்டீவ் செய்ததைப் போலவே செய்தார்கள், ஆனால் லிண்டா என்ற கற்பனையான பெண்ணின் பின்வரும் விளக்கத்தை மக்களுக்கு வழங்கினர். ",
  "model": "google_nmt",
  "n_reviews": 0,
  "start": 638.52,
  "end": 645.72
 },
 {
  "input": "Linda is 31 years old, single, outspoken, and very bright. ",
  "translatedText": "லிண்டாவுக்கு 31 வயது, தனிமையில் பேசக்கூடியவர், மிகவும் பிரகாசமானவர். ",
  "model": "google_nmt",
  "n_reviews": 0,
  "start": 646.4,
  "end": 650.62
 },
 {
  "input": "She majored in philosophy. ",
  "translatedText": "அவள் தத்துவத்தில் தேர்ச்சி பெற்றாள். ",
  "model": "google_nmt",
  "n_reviews": 0,
  "start": 651.14,
  "end": 652.16
 },
 {
  "input": "As a student she was deeply concerned with issues of discrimination and social justice, and also participated in the anti-nuclear demonstrations. ",
  "translatedText": "ஒரு மாணவராக இருந்தபோது, பாகுபாடு மற்றும் சமூக நீதி ஆகிய பிரச்சினைகளில் ஆழ்ந்த அக்கறை கொண்டிருந்தார், மேலும் அணுசக்தி எதிர்ப்பு ஆர்ப்பாட்டங்களிலும் பங்கேற்றார். ",
  "model": "google_nmt",
  "n_reviews": 0,
  "start": 652.64,
  "end": 659.54
 },
 {
  "input": "After seeing this people were asked what's more likely, 1. ",
  "translatedText": "இதைப் பார்த்த பிறகு, அதிக வாய்ப்பு என்ன என்று மக்களிடம் கேட்கப்பட்டது, 1. ",
  "model": "google_nmt",
  "n_reviews": 0,
  "start": 660.7,
  "end": 664.02
 },
 {
  "input": "That Linda is a bank teller, or 2. ",
  "translatedText": "லிண்டா ஒரு வங்கியில் பணம் கொடுப்பவர் அல்லது 2. ",
  "model": "google_nmt",
  "n_reviews": 0,
  "start": 664.34,
  "end": 666.46
 },
 {
  "input": "That Linda is a bank teller and is active in the feminist movement. ",
  "translatedText": "அந்த லிண்டா ஒரு வங்கியில் பணம் செலுத்துபவர் மற்றும் பெண்ணிய இயக்கத்தில் தீவிரமாக உள்ளார். ",
  "model": "google_nmt",
  "n_reviews": 0,
  "start": 666.92,
  "end": 669.9
 },
 {
  "input": "85%, 85% of participants said that the latter is more likely than the former, even though the set of bank tellers who are active in the feminist movement is a subset of the set of bank tellers. ",
  "translatedText": "85%, 85% பங்கேற்பாளர்கள், பெண்ணிய இயக்கத்தில் செயல்படும் வங்கிக் கணக்கு வழங்குபவர்களின் தொகுப்பானது, வங்கிக் கூறுபவர்களின் தொகுப்பின் துணைக்குழுவாக இருந்தாலும், முந்தையதை விட பிந்தையவர்கள் அதிகம் என்று கூறியுள்ளனர். ",
  "model": "google_nmt",
  "n_reviews": 0,
  "start": 671.22,
  "end": 683.32
 },
 {
  "input": "It has to be smaller. ",
  "translatedText": "இது சிறியதாக இருக்க வேண்டும். ",
  "model": "google_nmt",
  "n_reviews": 0,
  "start": 683.56,
  "end": 684.68
 },
 {
  "input": "So that's interesting enough, but what's fascinating is that there's a simple way that you can rephrase the question that dropped this error from 85% to 0. ",
  "translatedText": "எனவே இது மிகவும் சுவாரஸ்யமானது, ஆனால் கவர்ச்சிகரமான விஷயம் என்னவென்றால், இந்த பிழையை 85% இலிருந்து 0 ஆகக் குறைத்த கேள்வியை மீண்டும் எழுத ஒரு எளிய வழி உள்ளது. ",
  "model": "google_nmt",
  "n_reviews": 0,
  "start": 685.64,
  "end": 694.1
 },
 {
  "input": "Instead, if participants were told that there are 100 people who fit this description, and then asked to estimate how many of those 100 are bank tellers, and how many are bank tellers active in the feminist movement, nobody makes the error. ",
  "translatedText": "அதற்குப் பதிலாக, பங்கேற்பாளர்களிடம் இந்த விளக்கத்திற்குப் பொருந்தக்கூடிய 100 பேர் இருப்பதாகக் கூறப்பட்டால், அந்த 100 பேரில் எத்தனை பேர் வங்கிக் கணக்குத் தருபவர்கள் என்றும், பெண்ணிய இயக்கத்தில் செயல்படும் வங்கிச் சொல்பவர்கள் எத்தனை பேர் என்பதைக் கணக்கிடுமாறும் கேட்டால், யாரும் தவறில்லை. ",
  "model": "google_nmt",
  "n_reviews": 0,
  "start": 694.96,
  "end": 708.5
 },
 {
  "input": "Everybody correctly assigns a higher number to the first option than to the second. ",
  "translatedText": "ஒவ்வொருவரும் இரண்டாவது விருப்பத்தை விட முதல் விருப்பத்திற்கு அதிக எண்ணை சரியாக ஒதுக்குகிறார்கள். ",
  "model": "google_nmt",
  "n_reviews": 0,
  "start": 708.5,
  "end": 713.18
 },
 {
  "input": "It's weird, somehow phrases like 40 out of 100 kick our intuitions into gear much more effectively than 40%, much less 0.4, and much less abstractly referencing the idea of something being more or less likely. ",
  "translatedText": "இது வித்தியாசமானது, எப்படியோ 100க்கு 40 போன்ற சொற்றொடர்கள் 40% ஐ விட மிகவும் திறம்பட நம் உள்ளுணர்வை கியரில் உதைக்கின்றன, மிகவும் குறைவாக 0.4, மற்றும் ஏதாவது அதிகமாகவோ அல்லது குறைவாகவோ இருக்கலாம் என்ற கருத்தை மிகக் குறைவான சுருக்கமாகக் குறிப்பிடுகிறது. ",
  "model": "google_nmt",
  "n_reviews": 0,
  "start": 714.78,
  "end": 728.06
 },
 {
  "input": "That said, representative samples don't easily capture the continuous nature of probability. ",
  "translatedText": "பிரதிநிதி மாதிரிகள் நிகழ்தகவின் தொடர்ச்சியான தன்மையை எளிதில் பிடிக்காது. ",
  "model": "google_nmt",
  "n_reviews": 0,
  "start": 729.4,
  "end": 734.1
 },
 {
  "input": "So turning to area is a nice alternative, not just because of the continuity, but also because it's way easier to sketch out when you're sitting there pencil and paper puzzling over some problem. ",
  "translatedText": "எனவே பகுதிக்கு திரும்புவது ஒரு நல்ல மாற்றாகும், இது தொடர்ச்சியின் காரணமாக மட்டுமல்ல, நீங்கள் பென்சில் மற்றும் காகிதத்தில் ஏதாவது பிரச்சனையை குழப்பிக் கொண்டிருக்கும் போது ஓவியம் வரைவது எளிது. ",
  "model": "google_nmt",
  "n_reviews": 0,
  "start": 734.1,
  "end": 744.04
 },
 {
  "input": "People often think about probability as being the study of uncertainty, and that is of course how it's applied in science, but the actual math of probability, where all the formulas come from, is just the math of proportions, and in that context turning to geometry is exceedingly helpful. ",
  "translatedText": "நிகழ்தகவை நிச்சயமற்ற தன்மையின் ஆய்வு என்று மக்கள் அடிக்கடி நினைக்கிறார்கள், அது அறிவியலில் எவ்வாறு பயன்படுத்தப்படுகிறது, ஆனால் நிகழ்தகவின் உண்மையான கணிதம், எல்லா சூத்திரங்களும் எங்கிருந்து வருகின்றன என்பது விகிதாச்சாரத்தின் கணிதம் மட்டுமே, மேலும் அந்தச் சூழலில் மாறுகிறது. வடிவியல் மிகவும் பயனுள்ளதாக இருக்கிறது. ",
  "model": "google_nmt",
  "n_reviews": 0,
  "start": 745.22,
  "end": 761.02
 },
 {
  "input": "I mean, take a look at Bayes' theorem as a statement about proportions, whether that's proportions of people, of areas, whatever. ",
  "translatedText": "அதாவது, பேய்ஸின் தேற்றத்தை விகிதாச்சாரத்தைப் பற்றிய அறிக்கையாகப் பாருங்கள், அது மக்கள், பகுதிகள், எதுவாக இருந்தாலும் சரி. ",
  "model": "google_nmt",
  "n_reviews": 0,
  "start": 764.26,
  "end": 770.72
 },
 {
  "input": "Once you digest what it's saying, it's actually kind of obvious. ",
  "translatedText": "அது சொல்வதை நீங்கள் ஜீரணித்தவுடன், அது உண்மையில் வெளிப்படையானது. ",
  "model": "google_nmt",
  "n_reviews": 0,
  "start": 771.3,
  "end": 774.46
 },
 {
  "input": "Both sides tell you to look at the cases where the evidence is true, and then to consider the proportion of those cases where the hypothesis is also true. ",
  "translatedText": "ஆதாரங்கள் உண்மையாக இருக்கும் வழக்குகளைப் பார்க்கவும், பின்னர் கருதுகோள் உண்மையாக இருக்கும் வழக்குகளின் விகிதத்தைக் கருத்தில் கொள்ளவும் இரு தரப்பும் கூறுகின்றன. ",
  "model": "google_nmt",
  "n_reviews": 0,
  "start": 775.04,
  "end": 782.72
 },
 {
  "input": "That's it, that's all it's saying. ",
  "translatedText": "அவ்வளவுதான், அவ்வளவுதான் சொல்கிறது. ",
  "model": "google_nmt",
  "n_reviews": 0,
  "start": 783.24,
  "end": 784.64
 },
 {
  "input": "The right-hand side just spells out how to compute it. ",
  "translatedText": "வலது புறம் அதை எவ்வாறு கணக்கிடுவது என்பதை விவரிக்கிறது. ",
  "model": "google_nmt",
  "n_reviews": 0,
  "start": 784.86,
  "end": 786.9
 },
 {
  "input": "What's noteworthy is that such a straightforward fact about proportions can become hugely significant for science, for artificial intelligence, and really any situation where you want to quantify belief. ",
  "translatedText": "குறிப்பிடத்தக்க விஷயம் என்னவென்றால், விகிதாச்சாரத்தைப் பற்றிய இத்தகைய நேரடியான உண்மை அறிவியலுக்கும், செயற்கை நுண்ணறிவுக்கும், உண்மையில் நீங்கள் நம்பிக்கையை அளவிட விரும்பும் எந்த சூழ்நிலையிலும் மிகவும் குறிப்பிடத்தக்கதாக மாறும். ",
  "model": "google_nmt",
  "n_reviews": 0,
  "start": 787.54,
  "end": 797.92
 },
 {
  "input": "I hope to give you a better glimpse of that as we get into more examples. ",
  "translatedText": "நாங்கள் இன்னும் பல எடுத்துக்காட்டுகளைப் பெறும்போது, அதைப் பற்றிய சிறந்த பார்வையை உங்களுக்குத் தருவேன் என்று நம்புகிறேன். ",
  "model": "google_nmt",
  "n_reviews": 0,
  "start": 798.54,
  "end": 801.42
 },
 {
  "input": "But before more examples, we have a little bit of unfinished business with Steve. ",
  "translatedText": "ஆனால் இன்னும் சில எடுத்துக்காட்டுகளுக்கு முன், ஸ்டீவ் உடனான முடிக்கப்படாத வணிகம் எங்களிடம் உள்ளது. ",
  "model": "google_nmt",
  "n_reviews": 0,
  "start": 802.38,
  "end": 805.74
 },
 {
  "input": "As I mentioned, some psychologists debate Kahneman and Tversky's conclusion that the rational thing to do is to bring to mind the ratio of farmers to librarians. ",
  "translatedText": "நான் குறிப்பிட்டது போல், சில உளவியலாளர்கள் கான்மேன் மற்றும் ட்வெர்ஸ்கியின் முடிவைப் பற்றி விவாதிக்கின்றனர் சூழல் தெளிவற்றதாக இருப்பதாக அவர்கள் புகார் கூறுகிறார்கள். ",
  "model": "google_nmt",
  "n_reviews": 0,
  "start": 806.48,
  "end": 814.8
 },
 {
  "input": "They complain that the context is ambiguous. ",
  "translatedText": "",
  "model": "google_nmt",
  "n_reviews": 0,
  "start": 815.14,
  "end": 817.26
 },
 {
  "input": "I mean, who is Steve, exactly? ",
  "translatedText": "அதாவது, ஸ்டீவ் யார்? ",
  "model": "google_nmt",
  "n_reviews": 0,
  "start": 817.92,
  "end": 819.84
 },
 {
  "input": "Should you expect that he's a randomly sampled American? ",
  "translatedText": "அவர் தோராயமாக மாதிரி அமெரிக்கர் என்று நீங்கள் எதிர்பார்க்க வேண்டுமா? ",
  "model": "google_nmt",
  "n_reviews": 0,
  "start": 819.84,
  "end": 822.66
 },
 {
  "input": "Or would you be better to assume that he's a friend of the two psychologists interrogating you? ",
  "translatedText": "அல்லது அவர் உங்களை விசாரிக்கும் இரண்டு உளவியலாளர்களின் நண்பர் என்று நீங்கள் கருதுவது நன்றாக இருக்குமா? ",
  "model": "google_nmt",
  "n_reviews": 0,
  "start": 823.26,
  "end": 827.0
 },
 {
  "input": "Or maybe that he's someone you're personally likely to know? ",
  "translatedText": "அல்லது அவர் உங்களுக்கு தனிப்பட்ட முறையில் தெரிந்திருக்கக்கூடிய ஒருவரா? ",
  "model": "google_nmt",
  "n_reviews": 0,
  "start": 827.22,
  "end": 829.74
 },
 {
  "input": "This assumption determines the prior. ",
  "translatedText": "இந்த அனுமானம் முந்தையதை தீர்மானிக்கிறது. ",
  "model": "google_nmt",
  "n_reviews": 0,
  "start": 830.42,
  "end": 832.4
 },
 {
  "input": "I for one run into way more librarians in a given month than I do farmers. ",
  "translatedText": "ஒரு குறிப்பிட்ட மாதத்தில் நான் விவசாயிகளை விட அதிகமான நூலகர்களை உருவாக்கினேன். ",
  "model": "google_nmt",
  "n_reviews": 0,
  "start": 832.96,
  "end": 836.68
 },
 {
  "input": "Needless to say, the probability of a librarian or a farmer fitting this description is highly open to interpretation. ",
  "translatedText": "ஒரு நூலகர் அல்லது விவசாயி இந்த விளக்கத்தைப் பொருத்துவதற்கான நிகழ்தகவு விளக்கத்திற்கு மிகவும் திறந்திருக்கும் என்று சொல்லத் தேவையில்லை. ",
  "model": "google_nmt",
  "n_reviews": 0,
  "start": 837.5,
  "end": 843.52
 },
 {
  "input": "For our purposes, understanding the math, what I want to emphasize is that any question worth debating here can be pictured in the context of the diagram. ",
  "translatedText": "எங்கள் நோக்கங்களுக்காக, கணிதத்தைப் புரிந்துகொள்வது, நான் வலியுறுத்த விரும்புவது என்னவென்றால், இங்கே விவாதிக்கத் தகுந்த எந்தவொரு கேள்வியையும் வரைபடத்தின் பின்னணியில் சித்தரிக்கலாம். ",
  "model": "google_nmt",
  "n_reviews": 0,
  "start": 844.44,
  "end": 852.3
 },
 {
  "input": "Questions about the context shift around the prior, and questions about the personalities and stereotypes shift around the relevant likelihoods. ",
  "translatedText": "சூழல் பற்றிய கேள்விகள் முந்தையதைச் சுற்றி மாறுகின்றன, மேலும் ஆளுமைகள் மற்றும் ஸ்டீரியோடைப் பற்றிய கேள்விகள் தொடர்புடைய சாத்தியக்கூறுகளைச் சுற்றி மாறுகின்றன. ",
  "model": "google_nmt",
  "n_reviews": 0,
  "start": 853.0,
  "end": 860.58
 },
 {
  "input": "All that said, whether or not you buy this particular experiment, the ultimate point that evidence should not determine beliefs, but update them, is worth tattooing in your brain. ",
  "translatedText": "இந்த குறிப்பிட்ட பரிசோதனையை நீங்கள் வாங்கினாலும் வாங்காவிட்டாலும், சான்றுகள் நம்பிக்கைகளை தீர்மானிக்கக்கூடாது, ஆனால் அவற்றை புதுப்பிக்க வேண்டும் என்ற இறுதி புள்ளி, உங்கள் மூளையில் பச்சை குத்துவது மதிப்பு. ",
  "model": "google_nmt",
  "n_reviews": 0,
  "start": 861.1,
  "end": 871.0
 },
 {
  "input": "I'm in no position to say whether this does or does not run against natural human instinct. ",
  "translatedText": "இது இயற்கையான மனித உள்ளுணர்விற்கு எதிராக இயங்குகிறதா இல்லையா என்று சொல்ல முடியாத நிலையில் நான் இல்லை. ",
  "model": "google_nmt",
  "n_reviews": 0,
  "start": 871.8,
  "end": 876.5
 },
 {
  "input": "We'll leave that to the psychologists. ",
  "translatedText": "அதை உளவியலாளர்களிடம் விட்டுவிடுவோம். ",
  "model": "google_nmt",
  "n_reviews": 0,
  "start": 876.5,
  "end": 878.24
 },
 {
  "input": "What's more interesting to me is how we can reprogram our intuition to authentically reflect the implications of math, and bringing to mind the right image can often do just that. ",
  "translatedText": "எனக்கு மிகவும் சுவாரஸ்யமானது என்னவென்றால், கணிதத்தின் தாக்கங்களை உண்மையாகப் பிரதிபலிக்கும் வகையில் நமது உள்ளுணர்வை எவ்வாறு மறுபிரசுரம் செய்யலாம், மேலும் சரியான படத்தை மனதில் கொண்டு வருவது பெரும்பாலும் அதைச் செய்யலாம். ",
  "model": "google_nmt",
  "n_reviews": 0,
  "start": 878.92,
  "end": 888.06
 }
]